main.py
md5_brute_force-1.0.1.dist-info/entry_points.txt
md5_brute_force-1.0.1.dist-info/LICENSE.md
md5_brute_force-1.0.1.dist-info/WHEEL
md5_brute_force-1.0.1.dist-info/METADATA
md5_brute_force-1.0.1.dist-info/RECORD
