Metadata-Version: 2.1
Name: md5-brute-force
Version: 1.0.1
Summary: Python script for brute forcing an md5 hash.
Home-page: https://github.com/vsevolod-mineev/md5-brute-force
License: MIT
Author: Vsevolod Mineev
Author-email: vsevolod.mineev@gmail.com
Requires-Python: >=3.9,<3.11
Classifier: License :: OSI Approved :: MIT License
Classifier: Programming Language :: Python :: 3
Classifier: Programming Language :: Python :: 3.10
Classifier: Programming Language :: Python :: 3.9
Project-URL: Documentation, https://github.com/vsevolod-mineev/md5-brute-force
Project-URL: Repository, https://github.com/vsevolod-mineev/md5-brute-force
